SajadEnc/__init__.py
SajadNewNinja-1.dist-info/METADATA
SajadNewNinja-1.dist-info/WHEEL
SajadNewNinja-1.dist-info/top_level.txt
SajadNewNinja-1.dist-info/RECORD
