Metadata-Version: 2.1
Name: SajadNewNinja
Version: 1
Summary: an encryption library for sajad
Author: SajadNewNinja
Classifier: Programming Language :: Python :: 3
